[{"pk": 1, "model": "products.category", "fields": {"name": "architecture", "friendly_name": "Architecture", "image": "P1013155.JPG"}}, {"pk": 2, "model": "products.category", "fields": {"name": "castles", "friendly_name": "Castles", "image": "P1013843.JPG"}}, {"pk": 3, "model": "products.category", "fields": {"name": "vehicles", "friendly_name": "Vehicles", "image": "P6111236.JPG"}}, {"pk": 4, "model": "products.category", "fields": {"name": "landscapes", "friendly_name": "Landscapes", "image": "P1012158.JPG"}}, {"pk": 5, "model": "products.category", "fields": {"name": "nature", "friendly_name": "Nature", "image": "P7185473.JPG"}}]